composite_ufjc_scission/__init__.py
composite_ufjc_scission/characterizer.py
composite_ufjc_scission/composite_ufjc.py
composite_ufjc_scission/core.py
composite_ufjc_scission/default_parameters.py
composite_ufjc_scission/rate_dependence_scission.py
composite_ufjc_scission/scission_model.py
composite_ufjc_scission/utility.py
composite_ufjc_scission-1.4.0.dist-info/LICENSE
composite_ufjc_scission-1.4.0.dist-info/METADATA
composite_ufjc_scission-1.4.0.dist-info/WHEEL
composite_ufjc_scission-1.4.0.dist-info/top_level.txt
composite_ufjc_scission-1.4.0.dist-info/RECORD
